cluster_colors/__init__.py
cluster_colors/cluster_cluster.py
cluster_colors/cluster_members.py
cluster_colors/cluster_supercluster.py
cluster_colors/config.py
cluster_colors/cut_colors.py
cluster_colors/exceptions.py
cluster_colors/image_colors.py
cluster_colors/paths.py
cluster_colors/pool_colors.py
cluster_colors/py.typed
cluster_colors/type_hints.py
cluster_colors/vector_stacker.py
cluster_colors-2.5.0.dist-info/METADATA
cluster_colors-2.5.0.dist-info/WHEEL
cluster_colors-2.5.0.dist-info/top_level.txt
cluster_colors-2.5.0.dist-info/RECORD
