Metadata-Version: 2.1
Name: cluster_colors
Version: 2.5.0
Summary: Cluster rgb vectors with divisive kmedians
Author-email: Shay Hill <shay_public@hotmail.com>
License: MIT
Requires-Python: >=3.10
Requires-Dist: numpy
Requires-Dist: stacked-quantile >=0.4.0
Requires-Dist: paragraphs
Requires-Dist: basic-colormath >=0.4.0
Provides-Extra: dev
Requires-Dist: commitizen ; extra == 'dev'
Requires-Dist: pre-commit ; extra == 'dev'
Requires-Dist: pytest ; extra == 'dev'
Requires-Dist: tox ; extra == 'dev'
Requires-Dist: pillow ; extra == 'dev'
Requires-Dist: matplotlib ; extra == 'dev'
